AUTHORS.rst
CONTRIBUTING.rst
HISTORY.rst
LICENSE
MANIFEST.in
README.rst
setup.cfg
setup.py
django_view_hierarchy/__init__.py
django_view_hierarchy/apps.py
django_view_hierarchy/decorators.py
django_view_hierarchy/helpers.py
django_view_hierarchy/models.py
django_view_hierarchy/urls.py
django_view_hierarchy/utils.py
django_view_hierarchy/views.py
django_view_hierarchy.egg-info/PKG-INFO
django_view_hierarchy.egg-info/SOURCES.txt
django_view_hierarchy.egg-info/dependency_links.txt
django_view_hierarchy.egg-info/not-zip-safe
django_view_hierarchy.egg-info/top_level.txt