Metadata-Version: 1.1
Name: django-view-hierarchy
Version: 0.1.5
Summary: Hierarchical view system Python Django with breadcrumbs
Home-page: https://github.com/michaelpb/django-view-hierarchy
Author: michaelb
Author-email: michaelpb@gmail.com
License: GNU General Public License v3 or later (GPLv3+)
Keywords: django_view_hierarchy
Platform: UNKNOWN
Classifier: Development Status :: 3 - Alpha
Classifier: Intended Audience :: Developers
Classifier: Natural Language :: English
Classifier: Framework :: Django
Classifier: Framework :: Django :: 1.10
Classifier: Programming Language :: Python :: 3 :: Only
Classifier: Programming Language :: Python :: 3.5
Classifier: Programming Language :: Python :: 3.6
Classifier: License :: OSI Approved :: GNU General Public License v3 or later (GPLv3+)
